{
  "project_info": {
    "project_number": "347332665693",
    "firebase_url": "https://lt-scheduler.firebaseio.com",
    "project_id": "lt-scheduler",
    "storage_bucket": "lt-scheduler.appspot.com"
  },
  "client": [
    {
      "client_info": {
        "mobilesdk_app_id": "1:347332665693:android:b971f3b6144ca450dbc8b4",
        "android_client_info": {
          "package_name": "com.sabbir.ltscheduler"
        }
      },
      "oauth_client": [
        {
          "client_id": "347332665693-rvdejpop9en69hjuuemns9bomna78hbt.apps.googleusercontent.com",
          "client_type": 3
        }
      ],
      "api_key": [
        {
          "current_key": "AIzaSyCt-dsddSpdWkeW-YoRq6gFDnhYi2VbhHE"
        }
      ],
      "services": {
        "appinvite_service": {
          "other_platform_oauth_client": [
            {
              "client_id": "347332665693-rvdejpop9en69hjuuemns9bomna78hbt.apps.googleusercontent.com",
              "client_type": 3
            }
          ]
        }
      }
    }
  ],
  "configuration_version": "1"
}